MPU6050/MPU6050.py
MPU6050/Registers.py
MPU6050/__init__.py
mpu6050_PI-0.0.1.dist-info/METADATA
mpu6050_PI-0.0.1.dist-info/WHEEL
mpu6050_PI-0.0.1.dist-info/top_level.txt
mpu6050_PI-0.0.1.dist-info/RECORD
