Metadata-Version: 2.1
Name: mpu6050-PI
Version: 0.0.1
Summary: Easy to use python package to use MPU-6050. So get out your project setup and dream up some well-balanced projects
Home-page: https://github.com/Gagan-REPOSITORIES/sensors/tree/main/MPU6050/RaspberryPi
Author: ['Gagan Deepak', 'Aditya Chaudhary']
Author-email: ac3101282@gmail.com
License: MIT
Keywords: mpu6050 raspberry python accelerometer gyroscope
Classifier: License :: OSI Approved :: MIT License
Classifier: Topic :: Software Development :: Libraries
Classifier: Programming Language :: Python :: 2.7
Classifier: Programming Language :: Python :: 3
Classifier: Operating System :: POSIX :: Linux
